{
  "unpublishedPage": {
    "name": "investment",
    "slug": "investment",
    "layouts": [
      {
        "viewMode": false,
        "dsl": {
          "widgetName": "MainContainer",
          "backgroundColor": "none",
          "rightColumn": 1224,
          "snapColumns": 64,
          "detachFromLayout": true,
          "widgetId": "0",
          "topRow": 0,
          "bottomRow": 1440,
          "containerStyle": "none",
          "snapRows": 74,
          "parentRowSpace": 1,
          "type": "CANVAS_WIDGET",
          "canExtend": true,
          "version": 89,
          "minHeight": 760,
          "parentColumnSpace": 1,
          "dynamicBindingPathList": [],
          "leftColumn": 0
        },
        "layoutOnLoadActions": [
          [
            {
              "id": "investment_update_investment",
              "name": "update_investment",
              "confirmBeforeExecute": false,
              "pluginType": "API",
              "jsonPathKeys": [
                "appsmith.store.investment_id>"
              ],
              "timeoutInMillisecond": 10000
            }
          ]
        ],
        "layoutOnLoadActionErrors": [],
        "validOnPageLoadActions": true,
        "id": "investment",
        "deleted": false,
        "policies": [],
        "userPermissions": []
      }
    ],
    "userPermissions": [],
    "policies": [],
    "isHidden": false
  },
  "deleted": false,
  "gitSyncId": "66208e710e0d1c1635c20f2e_6620bf200e0d1c1635c21005"
}